changepoint_online/__init__.py
changepoint_online/focus.py
changepoint_online/mdfocus.py
changepoint_online/nunc.py
changepoint_online/tests/__init__.py
changepoint_online/tests/runtests.py
changepoint_online-1.2.0.dist-info/LICENSE
changepoint_online-1.2.0.dist-info/METADATA
changepoint_online-1.2.0.dist-info/WHEEL
changepoint_online-1.2.0.dist-info/top_level.txt
changepoint_online-1.2.0.dist-info/RECORD
