Metadata-Version: 2.1
Name: changepoint_online
Version: 1.2.0
Summary: A Collection of Methods for Online Changepoint Detection
Author-email: Daniel Grose <dan.grose@lancaster.ac.uk>, "Idris A. Eckley" <i.eckley@lancaster.ac.uk>, Paul Fearnhead <p.fearnhead@lancaster.ac.uk>, Liudmila Pishchagina <liudmila.pishchagina@univ-evry.fr>, Guillem Rigaill <guillem.rigaill@inrae.fr>, Gaetano Romano <g.romano@lancaster.ac.uk>, Vincent Runge <vincent.runge@univ-evry.fr>, Kes Ward <k.ward4@lancaster.ac.uk>
Maintainer-email: Daniel Grose <dan.grose@lancaster.ac.uk>, Gaetano Romano <g.romano@lancaster.ac.uk>
Project-URL: homepage, https://github.com/grosed/changepoint_online
Classifier: Programming Language :: Python :: 3
Classifier: License :: OSI Approved :: GNU General Public License v3 (GPLv3)
Classifier: Operating System :: OS Independent
Requires-Python: >=3.8
License-File: LICENSE
Requires-Dist: scipy
Requires-Dist: numpy
Requires-Dist: sortedcontainers
